exoscale/__init__.py
exoscale/openapi.json
exoscale/api/__init__.py
exoscale/api/exceptions.py
exoscale/api/generator.py
exoscale/api/v2.py
exoscale-0.14.0.dist-info/METADATA
exoscale-0.14.0.dist-info/WHEEL
exoscale-0.14.0.dist-info/licenses/LICENSE
exoscale-0.14.0.dist-info/RECORD
