Metadata-Version: 2.4
Name: exoscale
Version: 0.14.0
Summary: Clients for Exoscale IaaS APIs
Project-URL: Homepage, https://github.com/exoscale/python-exoscale
Project-URL: Bug Tracker, https://github.com/exoscale/python-exoscale/issues
Author-email: Exoscale <support@exoscale.com>
License-Expression: ISC
License-File: LICENSE
Classifier: Intended Audience :: Developers
Classifier: Intended Audience :: System Administrators
Classifier: License :: OSI Approved :: ISC License (ISCL)
Classifier: Operating System :: OS Independent
Classifier: Programming Language :: Python
Classifier: Programming Language :: Python :: 3.9
Classifier: Programming Language :: Python :: 3.10
Classifier: Programming Language :: Python :: 3.11
Classifier: Programming Language :: Python :: 3.12
Classifier: Programming Language :: Python :: 3.13
Requires-Python: >=3.8
Requires-Dist: requests-exoscale-auth>=1.1.2
Requires-Dist: requests>=2.22.0
